scPDA/__init__.py
scPDA/_loss.py
scPDA/_network.py
scPDA/_version.py
scPDA/api.py
scpda-0.6.0.dist-info/LICENSE
scpda-0.6.0.dist-info/METADATA
scpda-0.6.0.dist-info/WHEEL
scpda-0.6.0.dist-info/top_level.txt
scpda-0.6.0.dist-info/RECORD
